calligraphy/__init__.py
calligraphy/__main__.py
calligraphy/cli.py
calligraphy/export.py
calligraphy/utils.py
calligraphy/verify.py
calligraphy/commands/__init__.py
calligraphy/commands/export.py
calligraphy/commands/static.py
calligraphy/commands/verify.py
calligraphy-0.7.0.dist-info/COPYING
calligraphy-0.7.0.dist-info/METADATA
calligraphy-0.7.0.dist-info/WHEEL
calligraphy-0.7.0.dist-info/entry_points.txt
calligraphy-0.7.0.dist-info/top_level.txt
calligraphy-0.7.0.dist-info/RECORD
