Metadata-Version: 2.1
Name: calligraphy
Version: 0.7.0
Summary: A static blog generator.
Home-page: https://github.com/terrillo/calligraphy
Author: Terrillo Walls
Author-email: terrillo@terrillo.com
License: UNKNOWN
Project-URL: Bug Tracker, https://github.com/terrillo/calligraphy/issues
Project-URL: Documentation, https://github.com/terrillo/calligraphy
Project-URL: Source Code, https://github.com/terrillo/calligraphy
Platform: UNKNOWN
Classifier: Programming Language :: Python :: 3
Classifier: License :: OSI Approved :: MIT License
Classifier: Operating System :: OS Independent
Requires-Python: >=3.0.*
Requires-Dist: PyYAML (>=3.10)
Requires-Dist: Jinja2 (>=2.10.1)
Requires-Dist: docopt (==0.6.2)
Requires-Dist: Flask (==1.0.3)
